promptsearch/__init__.py
promptsearch/core.py
promptsearch/mutators.py
promptsearch/scorers.py
promptsearch-0.1.0.dist-info/licenses/LICENSE
promptsearch-0.1.0.dist-info/METADATA
promptsearch-0.1.0.dist-info/WHEEL
promptsearch-0.1.0.dist-info/top_level.txt
promptsearch-0.1.0.dist-info/RECORD
